ClosedAPI
