Metadata-Version: 2.1
Name: ClosedAPI
Version: 0.2
Home-page: https://github.com/kararasenok-gd/krrsnkapi
Author: Syirezz, Kararasenok_gd
Author-email: email@syirezz.com
License: MIT
